kogu/__init__.py
kogu/kogu.py
kogu-0.7.0.34.dist-info/DESCRIPTION.rst
kogu-0.7.0.34.dist-info/METADATA
kogu-0.7.0.34.dist-info/RECORD
kogu-0.7.0.34.dist-info/WHEEL
kogu-0.7.0.34.dist-info/metadata.json
kogu-0.7.0.34.dist-info/top_level.txt
tests/__init__.py
tests/kogu_test.py
