Metadata-Version: 2.0
Name: kogu
Version: 0.7.0.34
Summary: Kogu helper library
Home-page: https://kogu.io
Author: Proekspert AS
Author-email: hello@kogu.io
License: MIT
Platform: UNKNOWN
Classifier: Development Status :: 3 - Alpha
Classifier: Programming Language :: Python :: 2.7
Classifier: Programming Language :: Python :: 3.6
Requires-Python: >=2.7
